blacline/__init__.py
blacline/utils.py
blacline/schedule/__init__.py
blacline/schedule/allocation.py
blacline/schedule/basic_schedule.py
blacline/schedule/quick_schedule.py
blacline-0.1.1.dist-info/licenses/LICENSE
blacline-0.1.1.dist-info/METADATA
blacline-0.1.1.dist-info/WHEEL
blacline-0.1.1.dist-info/top_level.txt
blacline-0.1.1.dist-info/RECORD
