Metadata-Version: 2.4
Name: blacline
Version: 0.1.1
Summary: A Python package for bus scheduling, crew management, and timetable generation.
Author-email: Muniappan Puabi <95000am@gmail.com>
Maintainer-email: Muniappan Puabi <95000am@gmail.com>
License: MIT
Project-URL: bugs, https://github.com/ArvindManickam/blacline/issues
Project-URL: changelog, https://github.com/ArvindManickam/blacline/blob/master/changelog.md
Project-URL: homepage, https://github.com/ArvindManickam/blacline
Requires-Python: >=3.11.9
License-File: LICENSE
Requires-Dist: numpy==2.3.3
Requires-Dist: pandas==2.3.2
Requires-Dist: python-dateutil==2.9.0.post0
Requires-Dist: pytz==2025.2
Requires-Dist: six==1.17.0
Requires-Dist: tzdata==2025.2
Dynamic: license-file
